mestDS/__init__.py
mestDS/default_variables.py
mestDS/mestDS.py
mestDS/utils.py
mestDS/classes/ClimateHealthData.py
mestDS/classes/Evaluator.py
mestDS/classes/Feature.py
mestDS/classes/LossMetrics.py
mestDS/classes/ModelRunner.py
mestDS/classes/PDF.py
mestDS/classes/Region.py
mestDS/classes/Result.py
mestDS/classes/Simulation.py
mestDS/example_dsl/lagged_sickness_dsl.yaml
mestDS/example_dsl/weekly_simulation_and_eval_suites_dsl.yaml
mestds-0.0.4.dist-info/METADATA
mestds-0.0.4.dist-info/WHEEL
mestds-0.0.4.dist-info/licenses/LICENSE
mestds-0.0.4.dist-info/RECORD
