Metadata-Version: 2.4
Name: mestDS
Version: 0.0.4
Summary: mestDS with model evaluation
Project-URL: Homepage, https://github.com/martin-og-ingar/mestDS
Project-URL: Issues, https://github.com/martin-og-ingar/mestDS/issues
Author-email: Martin Bolle <martin.bolle97@hotmail.com>, Ingar Benonisen <ibenonisen@gmail.com>
License-File: LICENSE
Classifier: License :: OSI Approved :: MIT License
Classifier: Operating System :: OS Independent
Classifier: Programming Language :: Python :: 3
Requires-Python: >=3.8
Requires-Dist: chap-core==1.0.17
Requires-Dist: fpdf2
